pyebest/__init__.py
pyebest-0.1.7.dist-info/LICENSE.txt
pyebest-0.1.7.dist-info/METADATA
pyebest-0.1.7.dist-info/WHEEL
pyebest-0.1.7.dist-info/top_level.txt
pyebest-0.1.7.dist-info/RECORD
