Metadata-Version: 2.1
Name: pyebest
Version: 0.1.7
Summary: Python library for handling ebest api
Author: Hoseong Ryu
Author-email: riew610@gmail.com
Classifier: Programming Language :: Python :: 3
Classifier: License :: OSI Approved :: MIT License
Classifier: Operating System :: OS Independent
License-File: LICENSE.txt
